{
	"configurations" : 
	[
		{
			"directories" : 
			[
				{
					"build" : ".",
					"jsonFile" : "directory-.-Debug-d0094a50bb2071803777.json",
					"minimumCMakeVersion" : 
					{
						"string" : "3.25"
					},
					"projectIndex" : 0,
					"source" : ".",
					"targetIndexes" : 
					[
						0
					]
				}
			],
			"name" : "Debug",
			"projects" : 
			[
				{
					"directoryIndexes" : 
					[
						0
					],
					"name" : "32_ravenstva",
					"targetIndexes" : 
					[
						0
					]
				}
			],
			"targets" : 
			[
				{
					"directoryIndex" : 0,
					"id" : "32_ravenstva::@6890427a1f51a3e7e1df",
					"jsonFile" : "target-32_ravenstva-Debug-bc3047dff5c46e541b96.json",
					"name" : "32_ravenstva",
					"projectIndex" : 0
				}
			]
		}
	],
	"kind" : "codemodel",
	"paths" : 
	{
		"build" : "C:/Users/qRe/CLionProjects/32_ravenstva/cmake-build-debug",
		"source" : "C:/Users/qRe/CLionProjects/32_ravenstva"
	},
	"version" : 
	{
		"major" : 2,
		"minor" : 6
	}
}
